mkdocs_semiliterate/__init__.py
mkdocs_semiliterate/plugin.py
mkdocs_semiliterate-0.8.3.dist-info/LICENSE
mkdocs_semiliterate-0.8.3.dist-info/METADATA
mkdocs_semiliterate-0.8.3.dist-info/WHEEL
mkdocs_semiliterate-0.8.3.dist-info/entry_points.txt
mkdocs_semiliterate-0.8.3.dist-info/top_level.txt
mkdocs_semiliterate-0.8.3.dist-info/RECORD
