Metadata-Version: 2.1
Name: mkdocs-semiliterate
Version: 0.8.3
Summary: Extension of mkdocs-simple-plugin adding easy content inclusion
Home-page: http://studioinfinity.org/semiliterate
Author: Glen Whitney
Author-email: glen@studioinfinity.org
License: Apache-2.0
Project-URL: Issues, https://code.studioinfinity.org/glen/mkdocs-semiliterate/issues
Project-URL: Documentation, http://studioinfinity.org/semiliterate
Project-URL: Source Code, http://code.studioinfinity.org/glen/mkdocs-semiliterate
Project-URL: Source, http://code.studioinfinity.org/glen/mkdocs-semiliterate
Keywords: mkdocs literate
Classifier: Development Status :: 4 - Beta
Classifier: Intended Audience :: Developers
Classifier: Intended Audience :: Information Technology
Classifier: Programming Language :: Python
Classifier: Programming Language :: Python :: 3 :: Only
License-File: LICENSE
Requires-Dist: mkdocs~=1.4
Requires-Dist: mkdocs-simple-plugin==3.2.0
